Metadata-Version: 1.1
Name: django-gitrevision
Version: 0.1.5
Summary: Django git revision, simple add current git revision to request object for use in tempaltes and views.
